mcp_meteo/__init__.py
mcp_meteo/geocode.py
mcp_meteo/get_forecast.py
mcp_meteo/server.py
mcp_meteo-0.2.6.dist-info/METADATA
mcp_meteo-0.2.6.dist-info/WHEEL
mcp_meteo-0.2.6.dist-info/entry_points.txt
mcp_meteo-0.2.6.dist-info/top_level.txt
mcp_meteo-0.2.6.dist-info/RECORD
