Metadata-Version: 2.4
Name: mcp-meteo
Version: 0.2.6
Summary: Serveur MCP pour accéder aux données météo via Open-Meteo
Author-email: Kerryan Mace <kerryan.mace@student-cs.fr>
Project-URL: Homepage, https://github.com/KerryanOPMace/mcp-meteo
Project-URL: Repository, https://github.com/KerryanOPMace/mcp-meteo
Project-URL: Issues, https://github.com/KerryanOPMace/mcp-meteo/issues
Requires-Python: >=3.10
Requires-Dist: fastmcp
Requires-Dist: requests
Requires-Dist: setuptools
